{"type": "FeatureCollection", "features": [{"geometry": {"type": "Point", "coordinates": [112.57844608979383, 34.90771297283658]}, "properties": {"name": "吉利区"}, "type": "Feature"}, {"geometry": {"type": "Point", "coordinates": [111.53032151592866, 34.384781325472574]}, "properties": {"name": "洛宁县"}, "type": "Feature"}, {"geometry": {"type": "Point", "coordinates": [112.51010245895995, 34.80847298355747]}, "properties": {"name": "孟津县"}, "type": "Feature"}, {"geometry": {"type": "Point", "coordinates": [112.42662881788218, 34.08181280019692]}, "properties": {"name": "汝阳县"}, "type": "Feature"}, {"geometry": {"type": "Point", "coordinates": [112.11039725914627, 34.816208291016615]}, "properties": {"name": "新安县"}, "type": "Feature"}, {"geometry": {"type": "Point", "coordinates": [112.46473112944918, 34.39253580065887]}, "properties": {"name": "伊川县"}, "type": "Feature"}, {"geometry": {"type": "Point", "coordinates": [112.06062219761652, 34.522160596831064]}, "properties": {"name": "宜阳县"}, "type": "Feature"}, {"geometry": {"type": "Point", "coordinates": [112.73947490093714, 34.62692947939591]}, "properties": {"name": "偃师市"}, "type": "Feature"}, {"geometry": {"type": "Point", "coordinates": [112.05117069032353, 33.96754696007438]}, "properties": {"name": "嵩县"}, "type": "Feature"}, {"geometry": {"type": "Point", "coordinates": [111.62512685610545, 33.913868262361966]}, "properties": {"name": "栾川县"}, "type": "Feature"}, {"geometry": {"type": "Point", "coordinates": [112.44694219078494, 34.642573211321]}, "properties": {"name": "洛龙区"}, "type": "Feature"}, {"geometry": {"type": "Point", "coordinates": [112.50713407582546, 34.709001593601315]}, "properties": {"name": "瀍河回族区"}, "type": "Feature"}, {"geometry": {"type": "Point", "coordinates": [112.44095465652971, 34.71280234378383]}, "properties": {"name": "老城区"}, "type": "Feature"}, {"geometry": {"type": "Point", "coordinates": [112.3762169666557, 34.69455087236383]}, "properties": {"name": "西工区"}, "type": "Feature"}, {"geometry": {"type": "Point", "coordinates": [112.36534748293909, 34.66265714076322]}, "properties": {"name": "涧西区"}, "type": "Feature"}]}