{"type": "FeatureCollection", "features": [{"geometry": {"type": "Point", "coordinates": [103.84779390976054, 30.25506452611483]}, "properties": {"name": "彭山县"}, "type": "Feature"}, {"geometry": {"type": "Point", "coordinates": [103.4539060622777, 30.009619011256877]}, "properties": {"name": "丹棱县"}, "type": "Feature"}, {"geometry": {"type": "Point", "coordinates": [103.71662380103564, 30.079175706245735]}, "properties": {"name": "东坡区"}, "type": "Feature"}, {"geometry": {"type": "Point", "coordinates": [103.22010899008369, 29.741396045471053]}, "properties": {"name": "洪雅县"}, "type": "Feature"}, {"geometry": {"type": "Point", "coordinates": [103.84190941304948, 29.822731865573232]}, "properties": {"name": "青神县"}, "type": "Feature"}, {"geometry": {"type": "Point", "coordinates": [104.21697183174969, 29.98049323353032]}, "properties": {"name": "仁寿县"}, "type": "Feature"}]}